blapi_port-0.1.3.dist-info/METADATA
blapi_port-0.1.3.dist-info/WHEEL
blapi_port-0.1.3.dist-info/entry_points.txt
blapi_port-0.1.3.dist-info/licenses/LICENSE
blapi_port/__init__.py
blapi_port/login_port.py
blapi_port-0.1.3.dist-info/RECORD
