Metadata-Version: 2.1
Name: blapi-port
Version: 0.1.3
Summary: Some porting functions from the old version of bilibili-api-python
Author-Email: luyanci <luyancib@qq.com>
License: GPLv3
Requires-Python: >=3.9
Requires-Dist: bilibili-api-python>=17.1.0
